{
	"values": {
		"wetland_whimsy:aria_mushroom": {
			"chance": 0.65
		},
		"wetland_whimsy:aria_mushroom_block": {
			"chance": 0.85
		},
		"wetland_whimsy:aria_spores": {
			"chance": 0.2
		},
		"wetland_whimsy:bald_cypress_leaves": {
			"chance": 0.3
		},
		"wetland_whimsy:bloodcap_mushroom": {
			"chance": 0.65
		},
		"wetland_whimsy:carrot_seeds": {
			"chance": 0.3
		},
		"wetland_whimsy:cordgrass": {
			"chance": 0.4
		},
		"wetland_whimsy:cordgrass_thatch": {
			"chance": 0.9
		},
		"wetland_whimsy:pennywort": {
			"chance": 0.15
		}
	}
}
